{
  "author": "Sunan Abu Dawud",
  "hadith": {
    "hadithnumber": 1585,
    "arabicnumber": 1585,
    "text": "",
    "grades": [
      {
        "name": "Al-Albani",
        "grade": "Hasan"
      },
      {
        "name": "Muhammad Muhyi Al-Din Abdul Hamid",
        "grade": "Hasan"
      },
      {
        "name": "Shuaib Al Arnaut",
        "grade": "Hasan"
      },
      {
        "name": "Zubair Ali Zai",
        "grade": "Daif"
      }
    ],
    "reference": {
      "book": 9,
      "hadith": 30
    }
  }
}