{
  "author": "Sunan Ibn Majah",
  "hadith": {
    "hadithnumber": 2278,
    "arabicnumber": 2278,
    "text": "حدثنا عبد الله بن سعيد، حدثنا اسماعيل ابن علية، حدثنا داود بن ابي هند، عن سعيد بن ابي خيرة، عن الحسن، عن ابي هريرة، قال قال رسول الله صلى الله عليه وسلم \" لياتين على الناس زمان لا يبقى منهم احد الا اكل الربا فمن لم ياكل اصابه من غباره",
    "grades": [
      {
        "name": "Al-Albani",
        "grade": "Daif"
      },
      {
        "name": "Muhammad Fouad Abd al-Baqi",
        "grade": "Daif"
      },
      {
        "name": "Shuaib Al Arnaut",
        "grade": "Daif"
      },
      {
        "name": "Zubair Ali Zai",
        "grade": "Daif"
      }
    ],
    "reference": {
      "book": 12,
      "hadith": 142
    }
  }
}