{"author":"Sunan Ibn Majah","hadith":{"hadithnumber":620,"arabicnumber":620,"text":"حدثنا محمد بن رمح، انبانا الليث بن سعد، عن يزيد بن ابي حبيب، عن بكير بن عبد الله، عن المنذر بن المغيرة، عن عروة بن الزبير، ان فاطمة بنت ابي حبيش، حدثته انها، اتت رسول الله صلى الله عليه وسلم فشكت اليه الدم فقال رسول الله صلى الله عليه وسلم \" انما ذلك عرق فانظري اذا اتى قروك فلا تصلي فاذا مر القرء فتطهري ثم صلي ما بين القرء الى القرء","grades":[{"name":"Al-Albani","grade":"Sahih"},{"name":"Muhammad Fouad Abd al-Baqi","grade":"Sahih"},{"name":"Shuaib Al Arnaut","grade":"Sahih Lighairihi"},{"name":"Zubair Ali Zai","grade":"Daif"}],"reference":{"book":1,"hadith":354}}}