{
  "author": "Jami At Tirmidhi",
  "hadith": {
    "hadithnumber": 3604.05,
    "arabicnumber": 3604.05,
    "text": "حدثنا يحيى، اخبرنا يعلى بن عبيد، قال اخبرنا يحيى بن عبيد الله، عن ابيه، عن ابي هريرة، قال قال رسول الله صلى الله عليه وسلم \" ما من عبد يرفع يديه حتى يبدو ابطه يسال الله مسالة الا اتاها اياه ما لم يعجل \" . قالوا يا رسول الله وكيف عجلته قال \" يقول قد سالت وسالت ولم اعط شييا \" . وروى هذا الحديث الزهري عن ابي عبيد مولى ابن ازهر عن ابي هريرة عن النبي صلى الله عليه وسلم قال \" يستجاب لاحدكم ما لم يعجل يقول دعوت فلم يستجب لي",
    "grades": [],
    "reference": {
      "book": 48,
      "hadith": 239
    }
  }
}