{
  "author": "Sunan an Nasai",
  "hadith": {
    "hadithnumber": 5652,
    "arabicnumber": 5652,
    "text": "اخبرني محمد بن ادم بن سليمان، عن ابن فضيل، عن ابي سنان، عن محارب بن دثار، عن عبد الله بن بريدة، عن ابيه، قال قال رسول الله صلى الله عليه وسلم \" اني كنت نهيتكم عن زيارة القبور فزوروها ونهيتكم عن لحوم الاضاحي فوق ثلاثة ايام فامسكوا ما بدا لكم ونهيتكم عن النبيذ الا في سقاء فاشربوا في الاسقية كلها ولا تشربوا مسكرا",
    "grades": [
      {
        "name": "Abu Ghuddah",
        "grade": "Sahih"
      },
      {
        "name": "Al-Albani",
        "grade": "Sahih"
      },
      {
        "name": "Zubair Ali Zai",
        "grade": "Hasan"
      }
    ],
    "reference": {
      "book": 51,
      "hadith": 114
    }
  }
}