{
  "author": "Sahih al Bukhari",
  "hadith": {
    "hadithnumber": 1141,
    "arabicnumber": 1141,
    "text": "حدثنا عبد العزيز بن عبد الله، قال حدثني محمد بن جعفر، عن حميد، انه سمع انسا رضى الله عنه يقول كان رسول الله صلى الله عليه وسلم يفطر من الشهر حتى نظن ان لا يصوم منه، ويصوم حتى نظن ان لا يفطر منه شييا، وكان لا تشاء ان تراه من الليل مصليا الا رايته ولا نايما الا رايته. تابعه سليمان وابو خالد الاحمر عن حميد",
    "grades": [],
    "reference": {
      "book": 19,
      "hadith": 22
    }
  }
}