{"author":"Sunan an Nasai","hadith":{"hadithnumber":1412,"arabicnumber":1412,"text":"Telah mengabarkan kepada kami [Mahmud bin Ghailan] dia berkata; telah menceritakan kepada kami [Waki'] dia berkata; telah menceritakan kepada kami [Sufyan] dari [Hushain] bahwasanya Bisyr bin Marwan mengangkat tangannya pada hari Jum'at diatas mimbar, maka ['Umarah bin Ruwaibah Ats-Tsaqafi] mencelanya dan berkata; \"Rasulullah shallallahu 'alaihi wasallam tidak lebih dari ini.\" Ia mengisyaratkan dengan telunjuknya","grades":[{"name":"Abu Ghuddah","grade":"Sahih"},{"name":"Al-Albani","grade":"Sahih"},{"name":"Zubair Ali Zai","grade":"Sahih Muslim"}],"reference":{"book":14,"hadith":49}}}