{"author":"Sahih al Bukhari","hadith":{"hadithnumber":1900,"arabicnumber":1900,"text":"Сообщается, что Ибн ‘Умар, да будет доволен Аллах ими обоими, сказал: «Я слышал, как Посланник Аллаха ﷺ говорил: “Когда увидите его, (начинайте) поститься, и когда увидите его, прекращайте поститься, а если будет облачно и вы (его не увидите), тогда определяйте по нему”». \\nДругие (передатчики передали) от аль-Лейса, (который сказал): «Рассказали мне ‘Укъайль и Юнус: “(Когда увидите) молодой месяц”»","grades":[],"reference":{"book":30,"hadith":10}}}