{
  "author": "Sahih Muslim",
  "hadith": {
    "hadithnumber": 7267,
    "arabicnumber": 2892,
    "text": "وحدثني يعقوب بن ابراهيم الدورقي، وحجاج بن الشاعر، جميعا عن ابي عاصم، - قال حجاج حدثنا ابو عاصم، - اخبرنا عزرة بن ثابت، اخبرنا علباء بن احمر، حدثني ابو زيد، - يعني عمرو بن اخطب - قال صلى بنا رسول الله صلى الله عليه وسلم الفجر وصعد المنبر فخطبنا حتى حضرت الظهر فنزل فصلى ثم صعد المنبر فخطبنا حتى حضرت العصر ثم نزل فصلى ثم صعد المنبر فخطبنا حتى غربت الشمس فاخبرنا بما كان وبما هو كاين فاعلمنا احفظنا",
    "grades": [],
    "reference": {
      "book": 54,
      "hadith": 33
    }
  }
}