{"author":"Sunan an Nasai","hadith":{"hadithnumber":603,"arabicnumber":603,"text":"Yine İbn Abbâs (radıyallahü anh)’ten rivâyete göre, şöyle demiştir: sallallahü aleyhi ve sellem)’in arkasında, sekiz rekat bir arada ( yani öğle ile ikindi ) yedi rekat bir arada ( akşam ile yatsı) kıldım.) (Ebû Dâvûd, Salat: 274; Müslim, Salat-ül Müsafirin:)","grades":[{"name":"Abu Ghuddah","grade":"Sahih"},{"name":"Al-Albani","grade":"Sahih"},{"name":"Zubair Ali Zai","grade":"Sahih"}],"reference":{"book":6,"hadith":110}}}