{
  "author": "Sahih al Bukhari",
  "hadith": {
    "hadithnumber": 2671,
    "arabicnumber": 2671,
    "text": "حدثنا محمد بن بشار، حدثنا ابن ابي عدي، عن هشام، حدثنا عكرمة، عن ابن عباس رضى الله عنهما ان هلال بن امية، قذف امراته عند النبي صلى الله عليه وسلم بشريك بن سحماء، فقال النبي صلى الله عليه وسلم \" البينة او حد في ظهرك \". فقال يا رسول الله اذا راى احدنا على امراته رجلا ينطلق يلتمس البينة فجعل يقول \" البينة والا حد في ظهرك \". فذكر حديث اللعان",
    "grades": [],
    "reference": {
      "book": 52,
      "hadith": 33
    }
  }
}