{
  "author": "Sunan an Nasai",
  "hadith": {
    "hadithnumber": 3996,
    "arabicnumber": 3996,
    "text": "মুহাম্মদ ইবন আলা (রহঃ) ... আবদুল্লাহ (রাঃ) থেকে বর্ণিত। তিনি বলেন, কিয়ামতের দিন সর্বাগ্রে লোকের মাঝে খুনের বিচার করা হবে।",
    "grades": [
      {
        "name": "Abu Ghuddah",
        "grade": "Sahih Muquf"
      },
      {
        "name": "Al-Albani",
        "grade": "Sahih Muquf"
      },
      {
        "name": "Zubair Ali Zai",
        "grade": "Hasan"
      }
    ],
    "reference": {
      "book": 37,
      "hadith": 31
    }
  }
}