{
  "author": "Jami At Tirmidhi",
  "hadith": {
    "hadithnumber": 1944,
    "arabicnumber": 1944,
    "text": "حدثنا احمد بن محمد، حدثنا عبد الله بن المبارك، عن حيوة بن شريح، عن شرحبيل بن شريك، عن ابي عبد الرحمن الحبلي، عن عبد الله بن عمرو، قال قال رسول الله صلى الله عليه وسلم \" خير الاصحاب عند الله خيرهم لصاحبه وخير الجيران عند الله خيرهم لجاره \" . قال ابو عيسى هذا حديث حسن غريب . وابو عبد الرحمن الحبلي اسمه عبد الله بن يزيد",
    "grades": [
      {
        "name": "Ahmad Muhammad Shakir",
        "grade": "Sahih"
      },
      {
        "name": "Al-Albani",
        "grade": "Sahih"
      },
      {
        "name": "Zubair Ali Zai",
        "grade": "Isnaad Sahih"
      }
    ],
    "reference": {
      "book": 27,
      "hadith": 50
    }
  }
}