{"author":"Sunan an Nasai","hadith":{"hadithnumber":2821.2,"arabicnumber":2821.2,"text":"عبداللہ بن عباس رضی الله عنہما کہتے ہیں کہ زید بن ارقم رضی اللہ عنہ آئے تو ابن عباس رضی اللہ عنہما نے انہیں یاد دلاتے ہوئے کہا کہ آپ نے مجھے شکار کے گوشت کے بارے میں جسے رسول اللہ صلی اللہ علیہ وسلم کو ہدیہ کیا گیا تھا اور آپ محرم تھے کیا بتایا تھا؟ انہوں نے کہا: جی ہاں، نبی اکرم صلی اللہ علیہ وسلم کو ایک شخص شکار کے گوشت کا ایک پارچہ ( عضو ) بطور ہدیہ دیا، تو آپ صلی اللہ علیہ وسلم نے اسے لوٹا دیا اور فرمایا: ”ہم نہیں کھا سکتے، ہم احرام باندھے ہوئے ہیں“۔","grades":[],"reference":{"book":24,"hadith":204}}}