{
  "author": "Sunan an Nasai",
  "hadith": {
    "hadithnumber": 4406,
    "arabicnumber": 4406,
    "text": "اخبرنا عيسى بن احمد العسقلاني، - عسقلان بلخ - قال حدثنا ابن وهب، قال حدثني سفيان، عن هشام بن عروة، حدثه عن فاطمة بنت المنذر، عن اسماء بنت ابي بكر، قالت نحرنا فرسا على عهد رسول الله صلى الله عليه وسلم فاكلناه",
    "grades": [
      {
        "name": "Abu Ghuddah",
        "grade": "Sahih"
      },
      {
        "name": "Al-Albani",
        "grade": "Sahih"
      },
      {
        "name": "Zubair Ali Zai",
        "grade": "Sahih - Agreed Upon"
      }
    ],
    "reference": {
      "book": 43,
      "hadith": 46
    }
  }
}