{
  "author": "Sunan an Nasai",
  "hadith": {
    "hadithnumber": 441,
    "arabicnumber": 441,
    "text": "اخبرنا عمران بن يزيد، قال حدثنا اسماعيل بن عبد الله، قال حدثنا الاوزاعي، قال حدثنا محمد بن مسلم الزهري، قال حدثني سعيد بن المسيب، قال حدثني ابو هريرة، قال قال رسول الله صلى الله عليه وسلم \" اذا قام احدكم من الليل فلا يدخل يده في الاناء حتى يفرغ عليها مرتين او ثلاثا فان احدكم لا يدري اين باتت يده",
    "grades": [
      {
        "name": "Abu Ghuddah",
        "grade": "Sahih"
      },
      {
        "name": "Al-Albani",
        "grade": "Sahih"
      },
      {
        "name": "Zubair Ali Zai",
        "grade": "Isnaad Sahih"
      }
    ],
    "reference": {
      "book": 4,
      "hadith": 47
    }
  }
}