{"author":"Sunan an Nasai","hadith":{"hadithnumber":5497,"arabicnumber":5497,"text":"اخبرنا عمران بن بكار، قال حدثنا احمد بن خالد، قال حدثنا يونس، عن ابي اسحاق، - يعني اباه - عن عمرو بن ميمون، قال حججت مع عمر فسمعته يقول بجمع الا ان النبي صلى الله عليه وسلم كان يتعوذ من خمس \" اللهم اني اعوذ بك من البخل والجبن واعوذ بك من سوء العمر واعوذ بك من فتنة الصدر واعوذ بك من عذاب القبر","grades":[{"name":"Abu Ghuddah","grade":"Daif"},{"name":"Al-Albani","grade":"Daif"},{"name":"Zubair Ali Zai","grade":"Hasan"}],"reference":{"book":50,"hadith":70}}}