{
  "author": "Sunan Abu Dawud",
  "hadith": {
    "hadithnumber": 483,
    "arabicnumber": 483,
    "text": "",
    "grades": [
      {
        "name": "Al-Albani",
        "grade": "Sahih"
      },
      {
        "name": "Muhammad Muhyi Al-Din Abdul Hamid",
        "grade": "Sahih"
      },
      {
        "name": "Shuaib Al Arnaut",
        "grade": "Sahih"
      },
      {
        "name": "Zubair Ali Zai",
        "grade": "Sahih Muslim (554)"
      }
    ],
    "reference": {
      "book": 2,
      "hadith": 93
    }
  }
}