{
  "author": "Sunan an Nasai",
  "hadith": {
    "hadithnumber": 1614,
    "arabicnumber": 1614,
    "text": "حمید بن عبدالرحمٰن کہتے ہیں کہ رسول اللہ صلی اللہ علیہ وسلم نے فرمایا ہے: فرض نماز کے بعد سب سے افضل نماز قیام اللیل ( تہجد ) ہے، اور رمضان کے بعد سب سے افضل روزے محرم کے روزے ہیں ۔ شعبہ بن حجاج نے اسے مرسلاً روایت کیا ہے۔",
    "grades": [
      {
        "name": "Abu Ghuddah",
        "grade": "Sahih Lighairihi"
      },
      {
        "name": "Al-Albani",
        "grade": "Sahih"
      },
      {
        "name": "Zubair Ali Zai",
        "grade": "Hasan"
      }
    ],
    "reference": {
      "book": 20,
      "hadith": 17
    }
  }
}