{
  "author": "Sunan an Nasai",
  "hadith": {
    "hadithnumber": 1754,
    "arabicnumber": 1754,
    "text": "عبدالرحمٰن بن ابزیٰ رضی اللہ عنہ کہتے ہیں کہ رسول اللہ صلی اللہ علیہ وسلم وتر میں «سبح اسم ربك الأعلى»، «قل يا أيها الكافرون» اور «قل هو اللہ أحد» پڑھتے تھے، اور جب فارغ ہوتے تو «سبحان الملك القدوس» کہتے۔ ہشام نے اسے مرسلاً روایت کیا، ان کی روایت آگے آ رہی ہے ۱؎۔",
    "grades": [
      {
        "name": "Abu Ghuddah",
        "grade": "Sahih"
      },
      {
        "name": "Al-Albani",
        "grade": "Sahih"
      },
      {
        "name": "Zubair Ali Zai",
        "grade": "Hasan"
      }
    ],
    "reference": {
      "book": 20,
      "hadith": 157
    }
  }
}