{
  "author": "Sahih al Bukhari",
  "hadith": {
    "hadithnumber": 3544,
    "arabicnumber": 3544,
    "text": "Сообщается, что (однажды) Абу Джухайфа, да будет доволен им Аллах, сказал: «Я видел Пророка ﷺ и (могу сказать, что) аль-Хасан ибн ‘Али, да будет доволен Аллах ими обоими, похож на него». (Передатчик этого хадиса попросил Абу Джухайфу, да будет доволен им Аллах): «Опиши мне (Пророка ﷺ)». Он сказал: «Он был белокож, а чёрные волосы (его бороды) уже тронула седина. И Пророк ﷺ велел дать нам тринадцать верблюдиц, но скончался, прежде чем мы забрали их»",
    "grades": [],
    "reference": {
      "book": 61,
      "hadith": 53
    }
  }
}