{"author":"Sahih al Bukhari","hadith":{"hadithnumber":4577,"arabicnumber":4577,"text":"Сообщается, что Джабир, да будет доволен им Аллах, сказал: «(Когда я был болен,) Пророк ﷺ и Абу Бакр пришли в (квартал племени) бану салима, чтобы навестить меня. Пророк ﷺ увидел, что я лишился чувств, велел принести воды, совершил ею омовение и обрызгал меня (этой водой). Очнувшись, я спросил: “О Посланник Аллаха, что ты велишь мне сделать с моим имуществом?” — и тогда был ниспослан (аят, в котором говорится): “Аллах наказывает вам (завещать наследство) своим детям (так)…”»","grades":[],"reference":{"book":65,"hadith":99}}}