{
  "author": "Sahih Muslim",
  "hadith": {
    "hadithnumber": 3488,
    "arabicnumber": 1425.02,
    "text": "وحدثناه خلف بن هشام، حدثنا حماد بن زيد، ح وحدثنيه زهير بن حرب، حدثنا سفيان بن عيينة، ح وحدثنا اسحاق بن ابراهيم، عن الدراوردي، ح وحدثنا ابو بكر بن، ابي شيبة حدثنا حسين بن علي، عن زايدة، كلهم عن ابي حازم، عن سهل بن سعد، بهذا الحديث يزيد بعضهم على بعض غير ان في حديث زايدة قال \" انطلق فقد زوجتكها فعلمها من القران",
    "grades": [],
    "reference": {
      "book": 16,
      "hadith": 90
    }
  }
}