{"author":"Sunan Abu Dawud","hadith":{"hadithnumber":1385,"arabicnumber":1385,"text":"Telah menceritakan kepada kami [Al Qa'nabi] dari [Malik] dari [Abdullah bin Dinar] dari [Ibnu Umar] dia berkata; Rasulullah shallallahu 'alaihi wasallam bersabda: \"Carilah malam lailatul qadr di tujuh malam terakhir (bulan Ramadhan)","grades":[{"name":"Al-Albani","grade":"Sahih"},{"name":"Muhammad Muhyi Al-Din Abdul Hamid","grade":"Sahih"},{"name":"Shuaib Al Arnaut","grade":"Sahih"},{"name":"Zubair Ali Zai","grade":"Sahih Muslim (1165)"}],"reference":{"book":6,"hadith":15}}}