{"author":"Sahih al Bukhari","hadith":{"hadithnumber":6393,"arabicnumber":6393,"text":"Абу Хурайра, да будет доволен им Аллах, сказал: «Когда Пророк ﷺ говорил: “Да услышит Аллах тех, кто воздал Ему хвалу” в последнем рак‘ате вечерней молитвы, он совершал кунут (говоря): “О Аллах, спаси ‘Аййаша ибн Аби Раби‘у, о Аллах, спаси Саламу ибн Хишама, о Аллах, спаси аль-Валида ибн аль-Валида, о Аллах, спаси слабых из числа верующих! О Аллах, будь суров с племенем мудар и сделай так, чтобы голод продолжался для него столько же, сколько и во времена Йусуфа!»","grades":[],"reference":{"book":80,"hadith":88}}}