{
  "author": "Sahih al Bukhari",
  "hadith": {
    "hadithnumber": 6717,
    "arabicnumber": 6717,
    "text": "Сообщается со слов аль-Асвада, что, когда ‘Аиша захотела выкупить Бариру, её владельцы поставили ей условие, что право наследовать вольноотпущенника /аль-уаля/ останется за ними. Тогда она рассказала об этом Пророку ﷺ, и он сказал: «Выкупи её, а право наследовать вольноотпущенника /аль-уаля/ принадлежит тому, кто освободил его»",
    "grades": [],
    "reference": {
      "book": 84,
      "hadith": 10
    }
  }
}