{
  "author": "Sahih al Bukhari",
  "hadith": {
    "hadithnumber": 6957,
    "arabicnumber": 6957,
    "text": "Сообщается со слов Абу Хурайры, что Посланник Аллаха ﷺ сказал: «Сокровища (богатства) ваши в День воскресения будут в образе плешивого змея. Обладатель богатств будет убегать от него, но он будет преследовать его, говоря: “Я твои сокровища (богатства)!” И клянусь Аллахом, он не перестанет преследовать его, пока человек не протянет руку, а змей проглотит её»",
    "grades": [],
    "reference": {
      "book": 0,
      "hadith": 0
    }
  }
}