{
  "author": "Sunan Abu Dawud",
  "hadith": {
    "hadithnumber": 2052,
    "arabicnumber": 2052,
    "text": "حدثنا مسدد، وابو معمر قالا حدثنا عبد الوارث، عن حبيب، حدثني عمرو بن شعيب، عن سعيد المقبري، عن ابي هريرة، قال قال رسول الله صلى الله عليه وسلم \" لا ينكح الزاني المجلود الا مثله \" . وقال ابو معمر حدثني حبيب المعلم عن عمرو بن شعيب",
    "grades": [
      {
        "name": "Al-Albani",
        "grade": "Sahih"
      },
      {
        "name": "Muhammad Muhyi Al-Din Abdul Hamid",
        "grade": "Sahih"
      },
      {
        "name": "Zubair Ali Zai",
        "grade": "Isnaad Sahih"
      }
    ],
    "reference": {
      "book": 12,
      "hadith": 7
    }
  }
}