{"author":"Sunan Abu Dawud","hadith":{"hadithnumber":2838,"arabicnumber":2838,"text":"حدثنا ابن المثنى، حدثنا ابن ابي عدي، عن سعيد، عن قتادة، عن الحسن، عن سمرة بن جندب، ان رسول الله صلى الله عليه وسلم قال \" كل غلام رهينة بعقيقته تذبح عنه يوم سابعه ويحلق ويسمى \" . قال ابو داود ويسمى اصح كذا قال سلام بن ابي مطيع عن قتادة واياس بن دغفل واشعث عن الحسن . قال \" ويسمى \" . ورواه اشعث عن الحسن عن النبي صلى الله عليه وسلم قال \" ويسمى","grades":[{"name":"Al-Albani","grade":"Sahih"},{"name":"Muhammad Muhyi Al-Din Abdul Hamid","grade":"Sahih"},{"name":"Shuaib Al Arnaut","grade":"Sahih"},{"name":"Zubair Ali Zai","grade":"Sahih"}],"reference":{"book":16,"hadith":51}}}