{
  "author": "Sunan Abu Dawud",
  "hadith": {
    "hadithnumber": 3246,
    "arabicnumber": 3246,
    "text": "حدثنا عثمان بن ابي شيبة، حدثنا ابن نمير، حدثنا هاشم بن هاشم، اخبرني عبد الله بن نسطاس، من ال كثير بن الصلت انه سمع جابر بن عبد الله، قال قال رسول الله صلى الله عليه وسلم \" لا يحلف احد عند منبري هذا على يمين اثمة ولو على سواك اخضر الا تبوا مقعده من النار \" . او \" وجبت له النار",
    "grades": [
      {
        "name": "Al-Albani",
        "grade": "Sahih"
      },
      {
        "name": "Muhammad Muhyi Al-Din Abdul Hamid",
        "grade": "Sahih"
      },
      {
        "name": "Zubair Ali Zai",
        "grade": "Isnaad Sahih"
      }
    ],
    "reference": {
      "book": 22,
      "hadith": 5
    }
  }
}