{
  "author": "Sunan Abu Dawud",
  "hadith": {
    "hadithnumber": 3263,
    "arabicnumber": 3263,
    "text": "حدثنا عبد الله بن محمد النفيلي، حدثنا ابن المبارك، عن موسى بن عقبة، عن نافع، عن ابن عمر، قال : اكثر ما كان رسول الله صلى الله عليه وسلم يحلف بهذه اليمين : \" لا، ومقلب القلوب",
    "grades": [
      {
        "name": "Al-Albani",
        "grade": "Sahih"
      },
      {
        "name": "Muhammad Muhyi Al-Din Abdul Hamid",
        "grade": "Sahih"
      },
      {
        "name": "Zubair Ali Zai",
        "grade": "Sahih Bukhari (6617)"
      }
    ],
    "reference": {
      "book": 22,
      "hadith": 22
    }
  }
}