{"author":"Sunan Abu Dawud","hadith":{"hadithnumber":3787,"arabicnumber":3787,"text":"حدثنا احمد بن ابي سريج، اخبرني عبد الله بن جهم، حدثنا عمرو بن ابي قيس، عن ايوب السختياني، عن نافع، عن ابن عمر، قال نهى رسول الله صلى الله عليه وسلم عن الجلالة في الابل ان يركب عليها او يشرب من البانها","grades":[{"name":"Al-Albani","grade":"Hasan Sahih"},{"name":"Muhammad Muhyi Al-Din Abdul Hamid","grade":"Hasan Sahih"},{"name":"Shuaib Al Arnaut","grade":"Sahih"},{"name":"Zubair Ali Zai","grade":"Hasan"}],"reference":{"book":28,"hadith":52}}}