{
  "author": "Sunan Abu Dawud",
  "hadith": {
    "hadithnumber": 5097,
    "arabicnumber": 5097,
    "text": "حدثنا احمد بن محمد المروزي، وسلمة، - يعني ابن شبيب - قالا حدثنا عبد الرزاق، اخبرنا معمر، عن الزهري، قال حدثني ثابت بن قيس، ان ابا هريرة، قال سمعت رسول الله صلى الله عليه وسلم يقول \" الريح من روح الله \" . قال سلمة فروح الله تاتي بالرحمة وتاتي بالعذاب فاذا رايتموها فلا تسبوها وسلوا الله خيرها واستعيذوا بالله من شرها",
    "grades": [
      {
        "name": "Al-Albani",
        "grade": "Sahih"
      },
      {
        "name": "Muhammad Muhyi Al-Din Abdul Hamid",
        "grade": "Sahih"
      },
      {
        "name": "Zubair Ali Zai",
        "grade": "Isnaad Sahih"
      }
    ],
    "reference": {
      "book": 43,
      "hadith": 325
    }
  }
}