{"author":"Sunan Abu Dawud","hadith":{"hadithnumber":580,"arabicnumber":580,"text":"حدثنا سليمان بن داود المهري، حدثنا ابن وهب، اخبرني يحيى بن ايوب، عن عبد الرحمن بن حرملة، عن ابي علي الهمداني، قال سمعت عقبة بن عامر، يقول سمعت رسول الله صلى الله عليه وسلم يقول \" من ام الناس فاصاب الوقت فله ولهم ومن انتقص من ذلك شييا فعليه ولا عليهم","grades":[{"name":"Al-Albani","grade":"Hasan Sahih"},{"name":"Muhammad Muhyi Al-Din Abdul Hamid","grade":"Hasan Sahih"},{"name":"Shuaib Al Arnaut","grade":"Hasan"},{"name":"Zubair Ali Zai","grade":"Isnaad Sahih"}],"reference":{"book":2,"hadith":190}}}