{
  "author": "Sunan Abu Dawud",
  "hadith": {
    "hadithnumber": 673,
    "arabicnumber": 673,
    "text": "حدثنا محمد بن بشار، حدثنا عبد الرحمن، حدثنا سفيان، عن يحيى بن هاني، عن عبد الحميد بن محمود، قال صليت مع انس بن مالك يوم الجمعة فدفعنا الى السواري فتقدمنا وتاخرنا فقال انس كنا نتقي هذا على عهد رسول الله صلى الله عليه وسلم",
    "grades": [
      {
        "name": "Al-Albani",
        "grade": "Sahih"
      },
      {
        "name": "Muhammad Muhyi Al-Din Abdul Hamid",
        "grade": "Sahih"
      },
      {
        "name": "Zubair Ali Zai",
        "grade": "Isnaad Sahih"
      }
    ],
    "reference": {
      "book": 2,
      "hadith": 283
    }
  }
}