{
  "author": "Sunan Abu Dawud",
  "hadith": {
    "hadithnumber": 764,
    "arabicnumber": 764,
    "text": "حدثنا عمرو بن مرزوق، اخبرنا شعبة، عن عمرو بن مرة، عن عاصم العنزي، عن ابن جبير بن مطعم، عن ابيه، انه راى رسول الله صلى الله عليه وسلم يصلي صلاة قال عمرو لا ادري اى صلاة هي فقال \" الله اكبر كبيرا الله اكبر كبيرا الله اكبر كبيرا والحمد لله كثيرا والحمد لله كثيرا والحمد لله كثيرا وسبحان الله بكرة واصيلا \" . ثلاثا \" اعوذ بالله من الشيطان من نفخه ونفثه وهمزه \" . قال نفثه الشعر ونفخه الكبر وهمزه الموتة",
    "grades": [
      {
        "name": "Al-Albani",
        "grade": "Daif"
      },
      {
        "name": "Muhammad Muhyi Al-Din Abdul Hamid",
        "grade": "Daif"
      },
      {
        "name": "Shuaib Al Arnaut",
        "grade": "Hasan Lighairihi"
      },
      {
        "name": "Zubair Ali Zai",
        "grade": "Isnaad Hasan"
      }
    ],
    "reference": {
      "book": 2,
      "hadith": 374
    }
  }
}