{"author":"Sunan Abu Dawud","hadith":{"hadithnumber":780,"arabicnumber":780,"text":"حدثنا ابن المثنى، حدثنا عبد الاعلى، حدثنا سعيد، بهذا قال عن قتادة، عن الحسن، عن سمرة، قال سكتتان حفظتهما عن رسول الله صلى الله عليه وسلم . قال فيه قال سعيد قلنا لقتادة ما هاتان السكتتان قال اذا دخل في صلاته واذا فرغ من القراءة ثم قال بعد واذا قال { غير المغضوب عليهم ولا الضالين}","grades":[{"name":"Al-Albani","grade":"Daif"},{"name":"Muhammad Muhyi Al-Din Abdul Hamid","grade":"Daif"},{"name":"Zubair Ali Zai","grade":"Daif"}],"reference":{"book":2,"hadith":390}}}