{
  "author": "Muwatta Malik",
  "hadith": {
    "hadithnumber": 398,
    "arabicnumber": 398,
    "text": "وحدثني عن مالك، عن نعيم بن عبد الله المجمر، عن محمد بن عبد الله بن زيد، انه اخبره عن ابي مسعود الانصاري، انه قال اتانا رسول الله صلى الله عليه وسلم في مجلس سعد بن عبادة فقال له بشير بن سعد امرنا الله ان نصلي عليك يا رسول الله فكيف نصلي عليك قال فسكت رسول الله صلى الله عليه وسلم حتى تمنينا انه لم يساله ثم قال \" قولوا اللهم صل على محمد وعلى ال محمد كما صليت على ابراهيم وبارك على محمد وعلى ال محمد كما باركت على ال ابراهيم في العالمين انك حميد مجيد والسلام كما قد علمتم",
    "grades": [
      {
        "name": "Salim al-Hilali",
        "grade": "Mauquf Sahih"
      }
    ],
    "reference": {
      "book": 9,
      "hadith": 73
    }
  }
}