{"author":"Sunan Ibn Majah","hadith":{"hadithnumber":1805,"arabicnumber":1805,"text":"حدثنا بكر بن خلف، حدثنا عبد الرحمن بن مهدي، حدثنا سليمان بن كثير، حدثنا ابن شهاب، عن سالم بن عبد الله، عن ابيه، عن رسول الله صلى الله عليه وسلم قال اقراني سالم كتابا كتبه رسول الله صلى الله عليه وسلم في الصدقات قبل ان يتوفاه الله فوجدت فيه \" في اربعين شاة شاة الى عشرين وماية فاذا زادت واحدة ففيها شاتان الى مايتين فاذا زادت واحدة ففيها ثلاث شياه الى ثلاثماية فاذا كثرت ففي كل ماية شاة \" . ووجدت فيه \" لا يجمع بين متفرق ولا يفرق بين مجتمع \" . ووجدت فيه \" لا يوخذ في الصدقة تيس ولا هرمة ولا ذات عوار","grades":[{"name":"Al-Albani","grade":"Sahih"},{"name":"Muhammad Fouad Abd al-Baqi","grade":"Sahih"},{"name":"Zubair Ali Zai","grade":"Hasan"}],"reference":{"book":8,"hadith":23}}}