{"author":"Sahih al Bukhari","hadith":{"hadithnumber":1716,"arabicnumber":1716,"text":"حدثنا محمد بن كثير، اخبرنا سفيان، قال اخبرني ابن ابي نجيح، عن مجاهد، عن عبد الرحمن بن ابي ليلى، عن علي رضى الله عنه قال بعثني النبي صلى الله عليه وسلم فقمت على البدن، فامرني فقسمت لحومها، ثم امرني فقسمت جلالها وجلودها. قال سفيان وحدثني عبد الكريم، عن مجاهد، عن عبد الرحمن بن ابي ليلى، عن علي رضى الله عنه قال امرني النبي صلى الله عليه وسلم ان اقوم على البدن، ولا اعطي عليها شييا في جزارتها","grades":[],"reference":{"book":25,"hadith":194}}}