{"author":"Sunan Ibn Majah","hadith":{"hadithnumber":2138,"arabicnumber":2138,"text":"حدثنا هشام بن عمار، حدثنا اسماعيل بن عياش، عن بحير بن سعد، عن خالد بن معدان، عن المقدام بن معديكرب الزبيدي، عن رسول الله صلى الله عليه وسلم قال \" ما كسب الرجل كسبا اطيب من عمل يده وما انفق الرجل على نفسه واهله وولده وخادمه فهو صدقة","grades":[{"name":"Al-Albani","grade":"Sahih"},{"name":"Muhammad Fouad Abd al-Baqi","grade":"Sahih"},{"name":"Shuaib Al Arnaut","grade":"Hasan"},{"name":"Zubair Ali Zai","grade":"Hasan"}],"reference":{"book":12,"hadith":2}}}