{
  "author": "Sunan Abu Dawud",
  "hadith": {
    "hadithnumber": 2617,
    "arabicnumber": 2617,
    "text": "। ‘আব্দুল্লাহ ইবনু ‘আমর আল-গাযযী (রহঃ) সূত্রে বর্ণিত। তিনি বলেন, আমি শুনেছি আবু মুসহিরকে উবনা নামক জনপদ সম্পর্কে জিজ্ঞেস করা হলে তিনি বললেন, ‘আমরা তো ফিলিস্তীনের ‘ইউবনা’ নামক স্থানকেই ‘উবনা’ বলে জানি।",
    "grades": [
      {
        "name": "Al-Albani",
        "grade": "Maqtu"
      },
      {
        "name": "Muhammad Muhyi Al-Din Abdul Hamid",
        "grade": "Maqtu"
      },
      {
        "name": "Zubair Ali Zai",
        "grade": "Isnaad Sahih"
      }
    ],
    "reference": {
      "book": 15,
      "hadith": 141
    }
  }
}