{"author":"Sunan Abu Dawud","hadith":{"hadithnumber":4992,"arabicnumber":4992,"text":"حدثنا حفص بن عمر، حدثنا شعبة، ح وحدثنا محمد بن الحسين، حدثنا علي بن حفص، قال حدثنا شعبة، عن خبيب بن عبد الرحمن، عن حفص بن عاصم، - قال ابن حسين في حديثه - عن ابي هريرة، ان النبي صلى الله عليه وسلم قال \" كفى بالمرء اثما ان يحدث بكل ما سمع \" . قال ابو داود ولم يذكر حفص ابا هريرة . قال ابو داود ولم يسنده الا هذا الشيخ يعني علي بن حفص المدايني","grades":[{"name":"Al-Albani","grade":"Sahih"},{"name":"Muhammad Muhyi Al-Din Abdul Hamid","grade":"Sahih"},{"name":"Zubair Ali Zai","grade":"Sahih"}],"reference":{"book":43,"hadith":220}}}