{"author":"Jami At Tirmidhi","hadith":{"hadithnumber":790,"arabicnumber":790,"text":"حدثنا محمود بن غيلان، حدثنا عبد الرزاق، اخبرنا معمر، عن الزهري، عن سعيد بن المسيب، عن ابي هريرة، وعروة، عن عايشة، ان النبي صلى الله عليه وسلم كان يعتكف العشر الاواخر من رمضان حتى قبضه الله . قال وفي الباب عن ابى بن كعب وابي ليلى وابي سعيد وانس وابن عمر . قال ابو عيسى حديث ابي هريرة وعايشة حديث حسن صحيح","grades":[{"name":"Ahmad Muhammad Shakir","grade":"Sahih"},{"name":"Al-Albani","grade":"Sahih"},{"name":"Bashar Awad Maarouf","grade":"Hasan Sahih"},{"name":"Zubair Ali Zai","grade":"Sahih"}],"reference":{"book":8,"hadith":109}}}