{"author":"Sahih al Bukhari","hadith":{"hadithnumber":6678,"arabicnumber":6678,"text":"Сообщается, что Абу Муса (аль-Аш‘ари) сказал: «Однажды, мои товарищи послали меня к Пророку ﷺ, чтобы попросить у него снабдить верховыми животными. (Выслушав нас, Пророк ﷺ) сказал: “Клянусь Аллахом, ничем не стану я снабжать вас!” А дело было в том, что, когда я пришёл к нему, он был в состоянии гнева. А когда я пришёл к (Пророку ﷺ), он сказал: “Отправляйся к своим товарищам и скажи: “Поистине, Аллах (или: Поистине, Посланник Аллаха ﷺ) даёт вам (верховых животных)”»","grades":[],"reference":{"book":83,"hadith":55}}}