{"author":"Sunan Abu Dawud","hadith":{"hadithnumber":2819,"arabicnumber":2819,"text":"حدثنا عثمان بن ابي شيبة، حدثنا عمران بن عيينة، عن عطاء بن السايب، عن سعيد بن جبير، عن ابن عباس، قال جاءت اليهود الى النبي صلى الله عليه وسلم فقالوا ناكل مما قتلنا ولا ناكل مما قتل الله فانزل الله { ولا تاكلوا مما لم يذكر اسم الله عليه } الى اخر الاية","grades":[{"name":"Al-Albani","grade":"Munkar"},{"name":"Muhammad Muhyi Al-Din Abdul Hamid","grade":"Munkar"},{"name":"Zubair Ali Zai","grade":"Daif"}],"reference":{"book":16,"hadith":32}}}