{"author":"Sunan Ibn Majah","hadith":{"hadithnumber":4279,"arabicnumber":4279,"text":"حدثنا ابو بكر بن ابي شيبة، حدثنا علي بن مسهر، عن داود، عن الشعبي، عن مسروق، عن عايشة، قالت سالت رسول الله صلى الله عليه وسلم عن قوله {يوم تبدل الارض غير الارض والسموات } فاين تكون الناس يوميذ قال \" على الصراط","grades":[{"name":"Al-Albani","grade":"Sahih"},{"name":"Muhammad Fouad Abd al-Baqi","grade":"Sahih"},{"name":"Shuaib Al Arnaut","grade":"Sahih"},{"name":"Zubair Ali Zai","grade":"Sahih Muslim"}],"reference":{"book":37,"hadith":180}}}