{"author":"Jami At Tirmidhi","hadith":{"hadithnumber":1573,"arabicnumber":1573,"text":"حدثنا محمد بن بشار، حدثنا ابن ابي عدي، عن سعيد بن ابي عروبة، عن قتادة، عن سالم بن ابي الجعد، عن معدان بن ابي طلحة، عن ثوبان، قال قال رسول الله صلى الله عليه وسلم \" من فارق الروح الجسد وهو بريء من ثلاث الكنز والغلول والدين دخل الجنة \" . هكذا قال سعيد الكنز وقال ابو عوانة في حديثه الكبر ولم يذكر فيه عن معدان ورواية سعيد اصح","grades":[{"name":"Ahmad Muhammad Shakir","grade":"Shadh"},{"name":"Al-Albani","grade":"Shadh"},{"name":"Zubair Ali Zai","grade":"Daif"}],"reference":{"book":21,"hadith":34}}}