{"author":"Sahih al Bukhari","hadith":{"hadithnumber":1564,"arabicnumber":1564,"text":"حدثنا موسى بن اسماعيل، حدثنا وهيب، حدثنا ابن طاوس، عن ابيه، عن ابن عباس رضى الله عنهما قال كانوا يرون ان العمرة في اشهر الحج من افجر الفجور في الارض، ويجعلون المحرم صفرا ويقولون اذا برا الدبر، وعفا الاثر، وانسلخ صفر، حلت العمرة لمن اعتمر. قدم النبي صلى الله عليه وسلم واصحابه صبيحة رابعة مهلين بالحج، فامرهم ان يجعلوها عمرة فتعاظم ذلك عندهم فقالوا يا رسول الله اى الحل قال \" حل كله","grades":[],"reference":{"book":25,"hadith":50}}}