{
  "author": "Sahih al Bukhari",
  "hadith": {
    "hadithnumber": 2101,
    "arabicnumber": 2101,
    "text": "حدثني موسى بن اسماعيل، حدثنا عبد الواحد، حدثنا ابو بردة بن عبد الله، قال سمعت ابا بردة بن ابي موسى، عن ابيه رضى الله عنه قال قال رسول الله صلى الله عليه وسلم \" مثل الجليس الصالح والجليس السوء كمثل صاحب المسك، وكير الحداد، لا يعدمك من صاحب المسك اما تشتريه، او تجد ريحه، وكير الحداد يحرق بدنك او ثوبك او تجد منه ريحا خبيثة",
    "grades": [],
    "reference": {
      "book": 34,
      "hadith": 54
    }
  }
}