{
  "author": "Sahih al Bukhari",
  "hadith": {
    "hadithnumber": 4191,
    "arabicnumber": 4191,
    "text": "حدثني محمد بن هشام ابو عبد الله، حدثنا هشيم، عن ابي بشر، عن مجاهد، عن عبد الرحمن بن ابي ليلى، عن كعب بن عجرة، قال كنا مع رسول الله صلى الله عليه وسلم بالحديبية ونحن محرمون، وقد حصرنا المشركون قال وكانت لي وفرة فجعلت الهوام تساقط على وجهي، فمر بي النبي صلى الله عليه وسلم فقال \" ايوذيك هوام راسك \". قلت نعم. قال وانزلت هذه الاية {فمن كان منكم مريضا او به اذى من راسه ففدية من صيام او صدقة او نسك}",
    "grades": [],
    "reference": {
      "book": 64,
      "hadith": 231
    }
  }
}