{"author":"Sahih al Bukhari","hadith":{"hadithnumber":6542,"arabicnumber":6542,"text":"حدثنا معاذ بن اسد، اخبرنا عبد الله، اخبرنا يونس، عن الزهري، قال حدثني سعيد بن المسيب، ان ابا هريرة، حدثه قال سمعت رسول الله صلى الله عليه وسلم يقول \" يدخل من امتي زمرة هم سبعون الفا، تضيء وجوههم اضاءة القمر ليلة البدر \". وقال ابو هريرة فقام عكاشة بن محصن الاسدي يرفع نمرة عليه فقال يا رسول الله ادع الله ان يجعلني منهم. قال \" اللهم اجعله منهم \". ثم قام رجل من الانصار فقال يا رسول الله ادع الله ان يجعلني منهم. فقال \" سبقك عكاشة","grades":[],"reference":{"book":81,"hadith":131}}}