{
  "author": "Sahih al Bukhari",
  "hadith": {
    "hadithnumber": 336,
    "arabicnumber": 336,
    "text": "Передают со слов ‘Аиши о том, что как то она позаимствовала у Асмы ожерелье, которое пропало. Посланник Аллаха ﷺ отправил одного человека, (чтобы поискать ожерелье), которое он нашёл и их застало (время) молитвы, но у них не было воды и они совершили молитву (без омовения). Они пожаловались из-за этого Посланнику Аллаха ﷺ и Аллах ниспослал аят об очищении песком.\\nУсайд ибн Худайр сказал ‘Аише: «Да воздаст тебе Аллах добром! Клянусь Аллахом, не происходит с тобой что-то, что неприятно тебе, кроме, как Аллах делает тебе и мусульманам в этом благо»",
    "grades": [],
    "reference": {
      "book": 7,
      "hadith": 3
    }
  }
}