{"author":"Jami At Tirmidhi","hadith":{"hadithnumber":3624,"arabicnumber":3624,"text":"حدثنا محمد بن بشار، ومحمود بن غيلان، قالا انبانا ابو داود الطيالسي، حدثنا سليمان بن معاذ الضبي، عن سماك بن حرب، عن جابر بن سمرة، قال قال رسول الله صلى الله عليه وسلم \" ان بمكة حجرا كان يسلم على ليالي بعثت اني لاعرفه الان \" . قال هذا حديث حسن غريب","grades":[{"name":"Ahmad Muhammad Shakir","grade":"Sahih"},{"name":"Al-Albani","grade":"Sahih"},{"name":"Zubair Ali Zai","grade":"Sahih"}],"reference":{"book":49,"hadith":20}}}