{
  "author": "Jami At Tirmidhi",
  "hadith": {
    "hadithnumber": 3865,
    "arabicnumber": 3865,
    "text": "حدثنا ابو كريب، قال حدثنا عثمان بن ناجية، عن عبد الله بن مسلم ابي طيبة، عن عبد الله بن بريدة، عن ابيه، قال قال رسول الله صلى الله عليه وسلم \" ما من احد من اصحابي يموت بارض الا بعث قايدا ونورا لهم يوم القيامة \" . هذا حديث غريب . وروي هذا الحديث عن عبد الله بن مسلم ابي طيبة عن ابن بريدة عن النبي صلى الله عليه وسلم مرسلا وهو اصح",
    "grades": [
      {
        "name": "Ahmad Muhammad Shakir",
        "grade": "Daif"
      },
      {
        "name": "Al-Albani",
        "grade": "Daif"
      },
      {
        "name": "Zubair Ali Zai",
        "grade": "Daif"
      }
    ],
    "reference": {
      "book": 49,
      "hadith": 265
    }
  }
}