{"author":"Sunan Ibn Majah","hadith":{"hadithnumber":3324,"arabicnumber":3324,"text":"حدثنا محمد بن عبد الله بن نمير، حدثنا يونس بن بكير، حدثنا هشام بن عروة، عن ابيه، عن عايشة، قالت كانت امي تعالجني للسمنة تريد ان تدخلني على رسول الله صلى الله عليه وسلم فما استقام لها ذلك حتى اكلت القثاء بالرطب فسمنت كاحسن سمنة","grades":[{"name":"Al-Albani","grade":"Sahih"},{"name":"Muhammad Fouad Abd al-Baqi","grade":"Sahih"},{"name":"Zubair Ali Zai","grade":"Isnaad Sahih"}],"reference":{"book":29,"hadith":74}}}