{
  "author": "Sunan an Nasai",
  "hadith": {
    "hadithnumber": 1728,
    "arabicnumber": 1728,
    "text": "اخبرنا ابراهيم بن يعقوب، قال حدثنا ابو النعمان، قال حدثنا حماد بن سلمة، عن عاصم الاحول، عن ابي مجلز، ان ابا موسى، كان بين مكة والمدينة فصلى العشاء ركعتين ثم قام فصلى ركعة اوتر بها فقرا فيها بماية اية من النساء ثم قال ما الوت ان اضع قدمى حيث وضع رسول الله صلى الله عليه وسلم قدميه وانا اقرا بما قرا به رسول الله صلى الله عليه وسلم",
    "grades": [
      {
        "name": "Abu Ghuddah",
        "grade": "Sahih"
      },
      {
        "name": "Al-Albani",
        "grade": "Sahih"
      },
      {
        "name": "Zubair Ali Zai",
        "grade": "Daif"
      }
    ],
    "reference": {
      "book": 20,
      "hadith": 131
    }
  }
}