{
  "author": "Sunan an Nasai",
  "hadith": {
    "hadithnumber": 1798,
    "arabicnumber": 1798,
    "text": "اخبرني ايوب بن محمد، قال انبانا معمر بن سليمان، قال حدثنا زيد بن حبان، عن ابن جريج، عن عطاء، عن عنبسة بن ابي سفيان، عن ام حبيبة، قالت سمعت رسول الله صلى الله عليه وسلم يقول \" من صلى في يوم ثنتى عشرة ركعة بنى الله عز وجل له بيتا في الجنة \" . قال ابو عبد الرحمن عطاء لم يسمعه من عنبسة",
    "grades": [
      {
        "name": "Abu Ghuddah",
        "grade": "Sahih Lighairihi"
      },
      {
        "name": "Al-Albani",
        "grade": "Sahih"
      },
      {
        "name": "Zubair Ali Zai",
        "grade": "Hasan"
      }
    ],
    "reference": {
      "book": 20,
      "hadith": 201
    }
  }
}