{"author":"Sahih Muslim","hadith":{"hadithnumber":4495,"arabicnumber":"1720.01","text":"حدثني زهير بن حرب، حدثني شبابة، حدثني ورقاء، عن ابي الزناد، عن الاعرج، عن ابي هريرة، عن النبي صلى الله عليه وسلم قال \" بينما امراتان معهما ابناهما جاء الذيب فذهب بابن احداهما . فقالت هذه لصاحبتها انما ذهب بابنك انت . وقالت الاخرى انما ذهب بابنك . فتحاكمتا الى داود فقضى به للكبرى فخرجتا على سليمان بن داود عليهما السلام فاخبرتاه فقال ايتوني بالسكين اشقه بينكما . فقالت الصغرى لا يرحمك الله هو ابنها . فقضى به للصغرى \" . قال قال ابو هريرة والله ان سمعت بالسكين قط الا يوميذ ما كنا نقول الا المدية","grades":[],"reference":{"book":30,"hadith":26}}}