{
  "author": "Sunan Abu Dawud",
  "hadith": {
    "hadithnumber": 3555,
    "arabicnumber": 3555,
    "text": "حدثنا احمد بن حنبل، حدثنا عبد الرزاق، اخبرنا معمر، عن الزهري، عن ابي سلمة، عن جابر بن عبد الله، قال انما العمرى التي اجازها رسول الله صلى الله عليه وسلم ان يقول هي لك ولعقبك . فاما اذا قال هي لك ما عشت . فانها ترجع الى صاحبها",
    "grades": [
      {
        "name": "Al-Albani",
        "grade": "Sahih"
      },
      {
        "name": "Muhammad Muhyi Al-Din Abdul Hamid",
        "grade": "Sahih"
      },
      {
        "name": "Shuaib Al Arnaut",
        "grade": "Sahih"
      },
      {
        "name": "Zubair Ali Zai",
        "grade": "Sahih Muslim (1625)"
      }
    ],
    "reference": {
      "book": 24,
      "hadith": 140
    }
  }
}