{
  "author": "Sahih al Bukhari",
  "hadith": {
    "hadithnumber": 4600,
    "arabicnumber": 4600,
    "text": "حدثنا عبيد بن اسماعيل، حدثنا ابو اسامة، حدثنا هشام بن عروة، عن ابيه، عن عايشة رضى الله عنها {ويستفتونك في النساء قل الله يفتيكم فيهن} الى قوله {وترغبون ان تنكحوهن}. قالت هو الرجل تكون عنده اليتيمة، هو وليها ووارثها، فاشركته في ماله حتى في العذق، فيرغب ان ينكحها، ويكره ان يزوجها رجلا، فيشركه في ماله بما شركته فيعضلها فنزلت هذه الاية",
    "grades": [],
    "reference": {
      "book": 65,
      "hadith": 122
    }
  }
}